LICENSE
MANIFEST.in
README.rst
setup.cfg
setup.py
replaylib/__init__.py
replaylib/data.py
replaylib/noseplugin.py
replaylib/stubs.py
replaylib.egg-info/PKG-INFO
replaylib.egg-info/SOURCES.txt
replaylib.egg-info/dependency_links.txt
replaylib.egg-info/entry_points.txt
replaylib.egg-info/not-zip-safe
replaylib.egg-info/top_level.txt
replaylib/tests/__init__.py
replaylib/tests/servers.py
replaylib/tests/test_functional.py
replaylib/tests/test_plugin.py