Metadata-Version: 1.0
Name: replaylib
Version: 0.1
Summary: Record and replay httplib actions for testing.
Home-page: http://github.com/storborg/replaylib
Author: Scott Torborg, Mike Spindel
Author-email: storborg@mit.edu
License: GPL
Keywords: testing web replay
Platform: UNKNOWN
Classifier: Development Status :: 3 - Alpha
Classifier: License :: OSI Approved :: GNU General Public License (GPL)
Classifier: Intended Audience :: Developers
Classifier: Topic :: Software Development :: Testing
Classifier: Topic :: Internet
Classifier: Natural Language :: English
Classifier: Programming Language :: Python
